cython.py
Cython/CodeWriter.py
Cython/Coverage.py
Cython/Debugging.py
Cython/Shadow.py
Cython/Shadow.pyi
Cython/StringIOTree.py
Cython/TestUtils.py
Cython/Utils.py
Cython/__init__.py
Cython/__init__.pyi
Cython/py.typed
Cython/Build/BuildExecutable.py
Cython/Build/Cache.py
Cython/Build/Cythonize.py
Cython/Build/Dependencies.py
Cython/Build/Distutils.py
Cython/Build/Inline.py
Cython/Build/IpythonMagic.py
Cython/Build/SharedModule.py
Cython/Build/__init__.py
Cython/Build/Tests/TestCyCache.py
Cython/Build/Tests/TestCythonizeArgsParser.py
Cython/Build/Tests/TestDependencies.py
Cython/Build/Tests/TestInline.py
Cython/Build/Tests/TestIpythonMagic.py
Cython/Build/Tests/TestRecythonize.py
Cython/Build/Tests/TestStripLiterals.py
Cython/Build/Tests/__init__.py
Cython/Compiler/AnalysedTreeTransforms.py
Cython/Compiler/Annotate.py
Cython/Compiler/AutoDocTransforms.py
Cython/Compiler/Buffer.py
Cython/Compiler/Builtin.py
Cython/Compiler/CmdLine.py
Cython/Compiler/Code.pxd
Cython/Compiler/Code.py
Cython/Compiler/CodeGeneration.py
Cython/Compiler/CythonScope.py
Cython/Compiler/Dataclass.py
Cython/Compiler/DebugFlags.py
Cython/Compiler/Errors.py
Cython/Compiler/ExprNodes.py
Cython/Compiler/FlowControl.pxd
Cython/Compiler/FlowControl.py
Cython/Compiler/FusedNode.py
Cython/Compiler/Future.py
Cython/Compiler/Interpreter.py
Cython/Compiler/Lexicon.py
Cython/Compiler/LineTable.py
Cython/Compiler/Main.py
Cython/Compiler/MatchCaseNodes.py
Cython/Compiler/MemoryView.py
Cython/Compiler/ModuleNode.py
Cython/Compiler/Naming.py
Cython/Compiler/Nodes.py
Cython/Compiler/Optimize.py
Cython/Compiler/Options.py
Cython/Compiler/ParseTreeTransforms.pxd
Cython/Compiler/ParseTreeTransforms.py
Cython/Compiler/Parsing.pxd
Cython/Compiler/Parsing.py
Cython/Compiler/Pipeline.py
Cython/Compiler/PyrexTypes.py
Cython/Compiler/Pythran.py
Cython/Compiler/Scanning.pxd
Cython/Compiler/Scanning.py
Cython/Compiler/StringEncoding.py
Cython/Compiler/Symtab.py
Cython/Compiler/TreeFragment.py
Cython/Compiler/TreePath.py
cython-3.2.4.dist-info/METADATA
cython-3.2.4.dist-info/WHEEL
cython-3.2.4.dist-info/entry_points.txt
cython-3.2.4.dist-info/top_level.txt
cython-3.2.4.dist-info/RECORD
