Metadata-Version: 2.1
Name: Cython
Version: 3.2.4
Summary: The Cython compiler for writing C extensions in the Python language.
Home-page: https://cython.org/
Author: Robert Bradshaw, Stefan Behnel, David Woods, Greg Ewing, et al.
Author-email: cython-devel@python.org
License: Apache-2.0
Project-URL: Documentation, https://cython.readthedocs.io/
Project-URL: Donate, https://cython.readthedocs.io/en/latest/src/donating.html
Project-URL: Source Code, https://github.com/cython/cython
Project-URL: Bug Tracker, https://github.com/cython/cython/issues/
Project-URL: User Group, https://groups.google.com/g/cython-users
Classifier: Development Status :: 5 - Production/Stable
Classifier: Intended Audience :: Developers
Classifier: License :: OSI Approved :: Apache Software License
Classifier: Operating System :: OS Independent
Classifier: Programming Language :: Python
Classifier: Programming Language :: Python :: 3
Classifier: Programming Language :: Python :: 3.8
Classifier: Programming Language :: Python :: 3.9
Classifier: Programming Language :: Python :: 3.10
Classifier: Programming Language :: Python :: 3.11
Classifier: Programming Language :: Python :: 3.12
Classifier: Programming Language :: Python :: 3.13
Classifier: Programming Language :: Python :: 3.14
Classifier: Programming Language :: Python :: Implementation :: CPython
Classifier: Programming Language :: Python :: Implementation :: PyPy
Classifier: Programming Language :: Python :: Implementation :: Stackless
Classifier: Programming Language :: C
Classifier: Programming Language :: C++
Classifier: Programming Language :: Cython
Classifier: Topic :: Software Development :: Code Generators
Classifier: Topic :: Software Development :: Compilers
Classifier: Topic :: Software Development :: Libraries :: Python Modules
Classifier: Typing :: Typed
Requires-Python: >=3.8
